DiscordDatabase/DiscordDatabase.py
DiscordDatabase/__init__.py
DiscordDatabase/common_functions.py
DiscordDatabase/database.py
DiscordDatabase-0.1.3.dist-info/LICENSE
DiscordDatabase-0.1.3.dist-info/METADATA
DiscordDatabase-0.1.3.dist-info/WHEEL
DiscordDatabase-0.1.3.dist-info/top_level.txt
DiscordDatabase-0.1.3.dist-info/RECORD
