Metadata-Version: 2.1
Name: DiscordDatabase
Version: 0.1.3
Summary: CRUD database for discord bots, using discord text channels to store data
Home-page: https://github.com/ankushKun/DiscordDatabase
Author: Ankush Singh
Author-email: ankush4singh@gmail.com
License: MIT
Platform: UNKNOWN
Classifier: Intended Audience :: Developers
Classifier: License :: OSI Approved :: MIT License
Classifier: Programming Language :: Python :: 3
Classifier: Operating System :: OS Independent
License-File: LICENSE
